CHANGELOG.txt
LICENSE.txt
MANIFEST.in
README.txt
setup.cfg
setup.py
Mail.egg-info/PKG-INFO
Mail.egg-info/SOURCES.txt
Mail.egg-info/dependency_links.txt
Mail.egg-info/entry_points.txt
Mail.egg-info/not-zip-safe
Mail.egg-info/requires.txt
Mail.egg-info/top_level.txt
doc/index.txt
doc/source/api.rst
doc/source/index.rst
doc/source/manual.rst
mail/__init__.py
mail/service.py
test/README.txt
test/attachment.jpg
test/doc.py
test/test_mail.py