Metadata-Version: 1.0
Name: Mail
Version: 2.0.1
Summary: Simple wrapper over Python's email package for common operations.
Home-page: http://jimmyg.org/work/code/mail/index.html
Author: James Gardner
Author-email: UNKNOWN
License: GNU AGPLv3
Platform: UNKNOWN
Classifier: Development Status :: 3 - Alpha
Classifier: Topic :: Communications :: Email
Classifier: Environment :: Web Environment
Classifier: License :: OSI Approved :: GNU Affero General Public License v3
Classifier: Programming Language :: Python
